[{"word": "dishonest", "phonetic": "/d\u026a\u02c8s\u0252n\u026ast/", "phonetics": [{"text": "/d\u026a\u02c8s\u0252n\u026ast/", "audio": "https://api.dictionaryapi.dev/media/pronunciations/en/dishonest-uk.mp3", "sourceUrl": "https://commons.wikimedia.org/w/index.php?curid=94707868", "license": {"name": "BY-SA 4.0", "url": "https://creativecommons.org/licenses/by-sa/4.0"}}, {"text": "/d\u0268\u02c8s\u0251n\u026ast/", "audio": ""}], "meanings": [{"partOfSpeech": "adjective", "definitions": [{"definition": "Not honest.", "synonyms": [], "antonyms": []}, {"definition": "Interfering with honesty.", "synonyms": [], "antonyms": []}, {"definition": "Dishonourable; shameful; indecent; unchaste; lewd.", "synonyms": [], "antonyms": []}, {"definition": "Dishonoured; disgraced; disfigured.", "synonyms": [], "antonyms": []}], "synonyms": [], "antonyms": ["honest"]}], "license": {"name": "CC BY-SA 3.0", "url": "https://creativecommons.org/licenses/by-sa/3.0"}, "sourceUrls": ["https://en.wiktionary.org/wiki/dishonest"]}]