[{"word": "homework", "phonetic": "/\u02c8h\u0259\u028am\u02ccw\u025c\u02d0k/", "phonetics": [{"text": "/\u02c8h\u0259\u028am\u02ccw\u025c\u02d0k/", "audio": ""}, {"text": "/\u02c8ho\u028am\u02ccw\u025dk/", "audio": ""}], "meanings": [{"partOfSpeech": "noun", "definitions": [{"definition": "Work that is done at home, especially school exercises assigned by a teacher.", "synonyms": [], "antonyms": [], "example": "You must do your homework before you can watch television."}, {"definition": "Preliminary or preparatory work, such as research.", "synonyms": [], "antonyms": [], "example": "The speaker had certainly done his homework before delivering the lecture."}, {"definition": "Housework.", "synonyms": [], "antonyms": []}], "synonyms": [], "antonyms": []}], "license": {"name": "CC BY-SA 3.0", "url": "https://creativecommons.org/licenses/by-sa/3.0"}, "sourceUrls": ["https://en.wiktionary.org/wiki/homework"]}]